filedataclasses/__init__.py
filedataclasses/file.py
filedataclasses/json.py
filedataclasses/toml.py
filedataclasses/yaml.py
filedataclasses-0.1.0.dist-info/LICENSE.txt
filedataclasses-0.1.0.dist-info/METADATA
filedataclasses-0.1.0.dist-info/WHEEL
filedataclasses-0.1.0.dist-info/top_level.txt
filedataclasses-0.1.0.dist-info/RECORD
