Metadata-Version: 2.1
Name: filedataclasses
Version: 0.1.0
Summary: "Automatically load and dump your dataclasses 📂🙋"
Home-page: https://github.com/RealA10N/filedataclasses
Author: Alon Krymgand Osovsky
Author-email: downtown2u@gmail.com
License: UNKNOWN
Platform: UNKNOWN
Classifier: Programming Language :: Python :: 3
Classifier: Operating System :: OS Independent
Classifier: License :: OSI Approved :: Apache Software License
License-File: LICENSE.txt
Provides-Extra: all
Requires-Dist: toml (<1,>=0.10) ; extra == 'all'
Requires-Dist: pyyaml (<7,>=6.0) ; extra == 'all'
Provides-Extra: toml
Requires-Dist: toml (<1,>=0.10) ; extra == 'toml'
Provides-Extra: yaml
Requires-Dist: pyyaml (<7,>=6.0) ; extra == 'yaml'
